cdktf_cdktf_provider_vsphere/__init__.py
cdktf_cdktf_provider_vsphere/py.typed
cdktf_cdktf_provider_vsphere/_jsii/__init__.py
cdktf_cdktf_provider_vsphere/_jsii/provider-vsphere@11.2.0.jsii.tgz
cdktf_cdktf_provider_vsphere/compute_cluster/__init__.py
cdktf_cdktf_provider_vsphere/compute_cluster_host_group/__init__.py
cdktf_cdktf_provider_vsphere/compute_cluster_vm_affinity_rule/__init__.py
cdktf_cdktf_provider_vsphere/compute_cluster_vm_anti_affinity_rule/__init__.py
cdktf_cdktf_provider_vsphere/compute_cluster_vm_dependency_rule/__init__.py
cdktf_cdktf_provider_vsphere/compute_cluster_vm_group/__init__.py
cdktf_cdktf_provider_vsphere/compute_cluster_vm_host_rule/__init__.py
cdktf_cdktf_provider_vsphere/configuration_profile/__init__.py
cdktf_cdktf_provider_vsphere/content_library/__init__.py
cdktf_cdktf_provider_vsphere/content_library_item/__init__.py
cdktf_cdktf_provider_vsphere/custom_attribute/__init__.py
cdktf_cdktf_provider_vsphere/data_vsphere_compute_cluster/__init__.py
cdktf_cdktf_provider_vsphere/data_vsphere_compute_cluster_host_group/__init__.py
cdktf_cdktf_provider_vsphere/data_vsphere_configuration_profile/__init__.py
cdktf_cdktf_provider_vsphere/data_vsphere_content_library/__init__.py
cdktf_cdktf_provider_vsphere/data_vsphere_content_library_item/__init__.py
cdktf_cdktf_provider_vsphere/data_vsphere_custom_attribute/__init__.py
cdktf_cdktf_provider_vsphere/data_vsphere_datacenter/__init__.py
cdktf_cdktf_provider_vsphere/data_vsphere_datastore/__init__.py
cdktf_cdktf_provider_vsphere/data_vsphere_datastore_cluster/__init__.py
cdktf_cdktf_provider_vsphere/data_vsphere_datastore_stats/__init__.py
cdktf_cdktf_provider_vsphere/data_vsphere_distributed_virtual_switch/__init__.py
cdktf_cdktf_provider_vsphere/data_vsphere_dynamic/__init__.py
cdktf_cdktf_provider_vsphere/data_vsphere_folder/__init__.py
cdktf_cdktf_provider_vsphere/data_vsphere_guest_os_customization/__init__.py
cdktf_cdktf_provider_vsphere/data_vsphere_host/__init__.py
cdktf_cdktf_provider_vsphere-11.2.0.dist-info/LICENSE
cdktf_cdktf_provider_vsphere-11.2.0.dist-info/METADATA
cdktf_cdktf_provider_vsphere-11.2.0.dist-info/WHEEL
cdktf_cdktf_provider_vsphere-11.2.0.dist-info/top_level.txt
cdktf_cdktf_provider_vsphere-11.2.0.dist-info/RECORD
